setup.py
ipngnc/__init__.py
ipngnc/capabilities.py
ipngnc/debug.py
ipngnc/manager.py
ipngnc/xml_.py
ipngnc.egg-info/PKG-INFO
ipngnc.egg-info/SOURCES.txt
ipngnc.egg-info/dependency_links.txt
ipngnc.egg-info/top_level.txt
ipngnc/devices/__init__.py
ipngnc/devices/csr.py
ipngnc/devices/default.py
ipngnc/devices/huawei.py
ipngnc/devices/junos.py
ipngnc/devices/nexus.py
ipngnc/operations/__init__.py
ipngnc/operations/edit.py
ipngnc/operations/errors.py
ipngnc/operations/flowmon.py
ipngnc/operations/lock.py
ipngnc/operations/retrieve.py
ipngnc/operations/rpc.py
ipngnc/operations/session.py
ipngnc/operations/subscribe.py
ipngnc/operations/util.py
ipngnc/transport/__init__.py
ipngnc/transport/errors.py
ipngnc/transport/session.py
ipngnc/transport/ssh.py