Metadata-Version: 1.1
Name: ipngnc
Version: 0.1
Summary: Python library for NETCONF clients
Home-page: https://github.com/DavidJohnGee/ipngnc
Author: Shikhar Bhushan, Leonidas Poulopoulos, Ebben Aries, extended by David Gee
Author-email: shikhar@schmizz.net, leopoul@noc.grnet.gr, earies@juniper.net, david.gee@ipengineer.net
License: Apache License 2.0
Keywords: NETCONF,NETCONF Python client,Juniper Optimization,Cisco NXOS Optimization
Platform: Posix; OS X; Windows
Classifier: Development Status :: 5 - Production/Stable
Classifier: Programming Language :: Python :: 2.6
Classifier: Programming Language :: Python :: 2.7
Classifier: Topic :: System :: Networking
Classifier: Intended Audience :: Developers
Classifier: Operating System :: OS Independent
Classifier: Topic :: Software Development :: Libraries :: Python Modules
